Metadata-Version: 1.0
Name: rushed-distributions
Version: 0.1
Summary: Binomial and Gaussian distributions
Home-page: UNKNOWN
Author: Rushikesh Deotale
Author-email: UNKNOWN
License: UNKNOWN
Platform: UNKNOWN
